LICENSE
README.md
setup.cfg
setup.py
graphora/__init__.py
graphora/client.py
graphora/exceptions.py
graphora/models.py
graphora/utils.py
graphora.egg-info/PKG-INFO
graphora.egg-info/SOURCES.txt
graphora.egg-info/dependency_links.txt
graphora.egg-info/requires.txt
graphora.egg-info/top_level.txt