Metadata-Version: 2.4
Name: graphora
Version: 0.4.1
Summary: Python client for the Graphora API
Home-page: https://github.com/graphora/graphora-client
Author: Graphora Team
Author-email: support@graphora.io
Classifier: Programming Language :: Python :: 3
Classifier: Programming Language :: Python :: 3.7
Classifier: Programming Language :: Python :: 3.8
Classifier: Programming Language :: Python :: 3.9
Classifier: Programming Language :: Python :: 3.10
Classifier: License :: OSI Approved :: MIT License
Classifier: Operating System :: OS Independent
Requires-Python: >=3.7
License-File: LICENSE
Requires-Dist: requests>=2.25.0
Requires-Dist: pydantic>=1.8.0
Requires-Dist: pyyaml>=5.4.0
Dynamic: author
Dynamic: author-email
Dynamic: classifier
Dynamic: description
Dynamic: description-content-type
Dynamic: home-page
Dynamic: license-file
Dynamic: requires-dist
Dynamic: requires-python
Dynamic: summary
